<?xml version="1.0" encoding="UTF-8"?>
<!--

    The FreeBSD Copyright
    Copyright 1994-2008 The FreeBSD Project. All rights reserved.
    Copyright (C) 2013-2015 Philip Helger philip[at]helger[dot]com

    Redistribution and use in source and binary forms, with or without
    modification, are permitted provided that the following conditions are
    met:

       1. Redistributions of source code must retain the above copyright
       notice, this list of conditions and the following disclaimer.

       2. Redistributions in binary form must reproduce the above copyright
       notice, this list of conditions and the following disclaimer in the
       documentation and/or other materials provided with the distribution.

    THIS SOFTWARE IS PROVIDED BY THE FREEBSD PROJECT ``AS IS'' AND ANY
    EXPRESS OR IMPLIED WARRANTIES, INCLUDING, BUT NOT LIMITED TO, THE
    IMPLIED WARRANTIES OF MERCHANTABILITY AND FITNESS FOR A PARTICULAR
    PURPOSE ARE DISCLAIMED. IN NO EVENT SHALL THE FREEBSD PROJECT OR
    CONTRIBUTORS BE LIABLE FOR ANY DIRECT, INDIRECT, INCIDENTAL, SPECIAL,
    EXEMPLARY, OR CONSEQUENTIAL DAMAGES (INCLUDING, BUT NOT LIMITED TO,
    PROCUREMENT OF SUBSTITUTE GOODS OR SERVICES; LOSS OF USE, DATA, OR
    PROFITS; OR BUSINESS INTERRUPTION) HOWEVER CAUSED AND ON ANY THEORY OF
    LIABILITY, WHETHER IN CONTRACT, STRICT LIABILITY, OR TORT (INCLUDING
    NEGLIGENCE OR OTHERWISE) ARISING IN ANY WAY OUT OF THE USE OF THIS
    SOFTWARE, EVEN IF ADVISED OF THE POSSIBILITY OF SUCH DAMAGE.

    The views and conclusions contained in the software and documentation
    are those of the authors and should not be interpreted as representing
    official policies, either expressed or implied, of the FreeBSD Project.

-->
<changelog xmlns="http://www.phloc.com/ns/changelog/1.0" xmlns:xsi="http://www.w3.org/2001/XMLSchema-instance"
  xsi:schemaLocation="http://www.phloc.com/ns/changelog/1.0 schemas/changelog-1.0.xsd" version="1.0" component="as2-lib">
  <release date="2015-04-30" version="1.0.8" />
  <release date="2015-03-11" version="1.0.7" />
  <release date="2015-02-20" version="1.0.6" />
  <entry date="2015-02-19" category="tech" action="add">
    <change>
      <text locale="en">Added support for hash algorithms SHA-256, SHA-384 and SHA-512</text>
    </change>
  </entry>
  <release date="2015-01-30" version="1.0.5" />
  <release date="2014-11-03" version="1.0.4" />
  <entry date="2014-10-30" category="tech" action="update">
    <change>
      <text locale="en">Updated to ph-commons 5.2.0</text>
    </change>
  </entry>
  <entry date="2014-10-28" category="tech" action="update">
    <change>
      <text locale="en">Allowing incoming message to use the contained certificate for validation</text>
    </change>
  </entry>
  <release date="2014-10-28" version="1.0.3" />
  <entry date="2014-10-09" category="tech" action="update">
    <change>
      <text locale="en">Updated to ph-commons 5.1.0</text>
    </change>
  </entry>
  <release date="2014-10-03" version="1.0.2" />
  <entry date="2014-10-03" category="tech" action="fix">
    <change>
      <text locale="en">Fixed endless loop in AS2Message.toString() when an MDN is present</text>
    </change>
  </entry>
  <release date="2014-10-03" version="1.0.1" />
  <entry date="2014-10-02" category="api" action="change">
    <change>
      <text locale="en">Simplified Disposition field handling internally.</text>
    </change>
  </entry>
  <entry date="2014-10-02" category="api" action="add">
    <change>
      <text locale="en">Added possibility for client to automatically register receiver certificate in local certificate factory</text>
    </change>
  </entry>
  <release date="2014-09-29" version="1.0.0" />
</changelog>
